pulumiverse_vercel/__init__.py
pulumiverse_vercel/_inputs.py
pulumiverse_vercel/_utilities.py
pulumiverse_vercel/access_group.py
pulumiverse_vercel/access_group_project.py
pulumiverse_vercel/alias.py
pulumiverse_vercel/attack_challenge_mode.py
pulumiverse_vercel/custom_certificate.py
pulumiverse_vercel/custom_environment.py
pulumiverse_vercel/deployment.py
pulumiverse_vercel/dns_record.py
pulumiverse_vercel/edge_config.py
pulumiverse_vercel/edge_config_item.py
pulumiverse_vercel/edge_config_schema.py
pulumiverse_vercel/edge_config_token.py
pulumiverse_vercel/firewall_bypass.py
pulumiverse_vercel/firewall_config.py
pulumiverse_vercel/get_access_group.py
pulumiverse_vercel/get_access_group_project.py
pulumiverse_vercel/get_alias.py
pulumiverse_vercel/get_attack_challenge_mode.py
pulumiverse_vercel/get_custom_environment.py
pulumiverse_vercel/get_deployment.py
pulumiverse_vercel/get_domain_config.py
pulumiverse_vercel/get_dsync_groups.py
pulumiverse_vercel/get_edge_config.py
pulumiverse_vercel/get_edge_config_item.py
pulumiverse_vercel/get_edge_config_schema.py
pulumiverse_vercel/get_edge_config_token.py
pulumiverse_vercel/get_endpoint_verification.py
pulumiverse_vercel/get_file.py
pulumiverse_vercel/get_log_drain.py
pulumiverse_vercel/get_microfrontend_group.py
pulumiverse_vercel/get_microfrontend_group_membership.py
pulumiverse_vercel/get_prebuilt_project.py
pulumiverse_vercel/get_project.py
pulumiverse_vercel/get_project_deployment_retention.py
pulumiverse_vercel/get_project_directory.py
pulumiverse_vercel/get_project_members.py
pulumiverse_vercel/get_project_rolling_release.py
pulumiverse_vercel/get_shared_environment_variable.py
pulumiverse_vercel/get_team_config.py
pulumiverse_vercel/get_team_member.py
pulumiverse_vercel/integration_project_access.py
pulumiverse_vercel/log_drain.py
pulumiverse_vercel/microfrontend_group.py
pulumiverse_vercel/microfrontend_group_membership.py
pulumiverse_vercel/outputs.py
pulumiverse_vercel/project.py
pulumiverse_vercel-3.15.1.dist-info/METADATA
pulumiverse_vercel-3.15.1.dist-info/WHEEL
pulumiverse_vercel-3.15.1.dist-info/top_level.txt
pulumiverse_vercel-3.15.1.dist-info/RECORD
