Metadata-Version: 2.4
Name: pulumiverse_vercel
Version: 3.15.1
License: Apache-2.0
Project-URL: Repository, https://github.com/pulumiverse/pulumi-vercel
Keywords: pulumi,vercel,category/cloud
Requires-Python: >=3.8
Requires-Dist: parver>=0.2.1
Requires-Dist: pulumi<4.0.0,>=3.136.0
Requires-Dist: semver>=2.8.1
Requires-Dist: typing-extensions>=4.11; python_version < "3.11"
